hemse/__init__.py
hemse/app.py
hemse/version.py
hemse/common/__init__.py
hemse/common/color.py
hemse/pages/add_activity.py
hemse/pages/add_weight.py
hemse/pages/home.py
hemse/pages/telemetry.py
hemse-1.0.2.dist-info/LICENSE
hemse-1.0.2.dist-info/METADATA
hemse-1.0.2.dist-info/WHEEL
hemse-1.0.2.dist-info/top_level.txt
hemse-1.0.2.dist-info/RECORD
